{

	
	"shortContent" : "The presence of a synapse creature
in an encounter grants the Fearless talent to all other Tyranid
creatures and also suppresses the effects of the Instinctive
Behaviour Trait in those creatures that possess it. Range = WP Bonus x10m. ",
	
	"content" : "A Tyranid creature with this trait is a node from which the
controlling and unifying presence of the Hive Mind guides the
actions of other Tyranids. The presence of a synapse creature
in an encounter grants the Fearless talent to all other Tyranid
creatures and also suppresses the effects of the Instinctive
Behaviour Trait in those creatures that possess it (see page
132 in this chapter for more details). If an exact range for this
effect is needed, it can be considered equal to the creature’s
Willpower Bonus x10 metres.",

	"extraSubCategories" : [],
	
	"GMOnly" : false,
	
	"pageNumber" : 135
}