{

	
	"shortContent" : "The character can Ready as a Free Action
when armed with a pistol or basic ranged weapon, or a melee
weapon that can be wielded in one hand.",
	
	"content" : "The character has practiced so frequently with his weapons
that they practically leap into his hands in response to a
simple thought. The character can Ready as a Free Action
when armed with a pistol or basic ranged weapon, or a melee
weapon that can be wielded in one hand.",

	"extraSubCategories" : 
	[ 
		["Prerequisites", "Adeptus Astartes, may not be taken by characters with a Psy Rating"]
	],
	
	"GMOnly" : false,
	
	"pageNumber" : 124
}